aiopromql/__init__.py
aiopromql/client.py
aiopromql/utils.py
aiopromql/models/__init__.py
aiopromql/models/core.py
aiopromql/models/prometheus.py
aiopromql-0.1.2.dist-info/METADATA
aiopromql-0.1.2.dist-info/WHEEL
aiopromql-0.1.2.dist-info/licenses/LICENSE
aiopromql-0.1.2.dist-info/RECORD
