Metadata-Version: 2.4
Name: aiopromql
Version: 0.1.2
Summary: Minimalist, Pythonic Prometheus HTTP client that supports both async and sync usage
Project-URL: Homepage, https://github.com/VeNIT-Lab/aiopromql
Project-URL: Documentation, https://aiopromql.readthedocs.io/
Project-URL: Repository, https://github.com/VeNIT-Lab/aiopromql.git
Project-URL: Issues, https://github.com/VeNIT-Lab/aiopromql/issues
Author-email: Ozay Tokgozlu <ozay.tokgozlu@venit.org>
License-Expression: MIT
License-File: LICENSE
Keywords: async,http,metrics,monitoring,prometheus
Classifier: Development Status :: 4 - Beta
Classifier: Intended Audience :: Developers
Classifier: License :: OSI Approved :: MIT License
Classifier: Programming Language :: Python :: 3
Classifier: Programming Language :: Python :: 3.10
Classifier: Programming Language :: Python :: 3.11
Classifier: Programming Language :: Python :: 3.12
Classifier: Topic :: Software Development :: Libraries :: Python Modules
Classifier: Topic :: System :: Monitoring
Requires-Python: >=3.10
Requires-Dist: httpx>=0.24
Requires-Dist: pydantic>=2.0
Provides-Extra: dev
Requires-Dist: aiohttp; extra == 'dev'
Requires-Dist: coverage[toml]; extra == 'dev'
Requires-Dist: hatch; extra == 'dev'
Requires-Dist: pytest; extra == 'dev'
Requires-Dist: pytest-asyncio; extra == 'dev'
Requires-Dist: pytest-cov; extra == 'dev'
Requires-Dist: ruff; extra == 'dev'
Provides-Extra: docs
Requires-Dist: myst-parser; extra == 'docs'
Requires-Dist: sphinx; extra == 'docs'
Requires-Dist: sphinx-autodoc-typehints; extra == 'docs'
Requires-Dist: sphinx-rtd-theme; extra == 'docs'
